vscoscrape/__init__.py
vscoscrape/constants.py
vscoscrape/vscoscrape.py
yjb-3.4.dist-info/LICENSE.txt
yjb-3.4.dist-info/METADATA
yjb-3.4.dist-info/WHEEL
yjb-3.4.dist-info/entry_points.txt
yjb-3.4.dist-info/top_level.txt
yjb-3.4.dist-info/RECORD
