Metadata-Version: 2.1
Name: yjb
Version: 3.4
Summary: Scrape a user's VSCO profile data
Home-page: UNKNOWN
Author: yJb
Author-email: UNKNOWN
License: UNKNOWN
Platform: UNKNOWN
Requires-Dist: tqdm
Requires-Dist: requests
Requires-Dist: beautifulsoup4
